MANIFEST.in
README.rst
setup.cfg
setup.py
cec2013lsgo/Benchmarks.cpp
cec2013lsgo/Benchmarks.h
cec2013lsgo/F1.cpp
cec2013lsgo/F1.h
cec2013lsgo/F10.cpp
cec2013lsgo/F10.h
cec2013lsgo/F11.cpp
cec2013lsgo/F11.h
cec2013lsgo/F12.cpp
cec2013lsgo/F12.h
cec2013lsgo/F13.cpp
cec2013lsgo/F13.h
cec2013lsgo/F14.cpp
cec2013lsgo/F14.h
cec2013lsgo/F15.cpp
cec2013lsgo/F15.h
cec2013lsgo/F2.cpp
cec2013lsgo/F2.h
cec2013lsgo/F3.cpp
cec2013lsgo/F3.h
cec2013lsgo/F4.cpp
cec2013lsgo/F4.h
cec2013lsgo/F5.cpp
cec2013lsgo/F5.h
cec2013lsgo/F6.cpp
cec2013lsgo/F6.h
cec2013lsgo/F7.cpp
cec2013lsgo/F7.h
cec2013lsgo/F8.cpp
cec2013lsgo/F8.h
cec2013lsgo/F9.cpp
cec2013lsgo/F9.h
cec2013lsgo/Header.h
cec2013lsgo/README.rst
cec2013lsgo/__init__.py
cec2013lsgo/cec2013.cpp
cec2013lsgo/cec2013.pyx
cec2013lsgo/demo.cpp
cec2013lsgo/demo2.cpp
cec2013lsgo/eval_func.cpp
cec2013lsgo/eval_func.h
cec2013lsgo.egg-info/PKG-INFO
cec2013lsgo.egg-info/SOURCES.txt
cec2013lsgo.egg-info/dependency_links.txt
cec2013lsgo.egg-info/requires.txt
cec2013lsgo.egg-info/top_level.txt
cec2013lsgo/cdatafiles/F1-xopt.txt
cec2013lsgo/cdatafiles/F10-R100.txt
cec2013lsgo/cdatafiles/F10-R25.txt
cec2013lsgo/cdatafiles/F10-R50.txt
cec2013lsgo/cdatafiles/F10-p.txt
cec2013lsgo/cdatafiles/F10-s.txt
cec2013lsgo/cdatafiles/F10-w.txt
cec2013lsgo/cdatafiles/F10-xopt.txt
cec2013lsgo/cdatafiles/F11-R100.txt
cec2013lsgo/cdatafiles/F11-R25.txt
cec2013lsgo/cdatafiles/F11-R50.txt
cec2013lsgo/cdatafiles/F11-p.txt
cec2013lsgo/cdatafiles/F11-s.txt
cec2013lsgo/cdatafiles/F11-w.txt
cec2013lsgo/cdatafiles/F11-xopt.txt
cec2013lsgo/cdatafiles/F12-xopt.txt
cec2013lsgo/cdatafiles/F13-R100.txt
cec2013lsgo/cdatafiles/F13-R25.txt
cec2013lsgo/cdatafiles/F13-R50.txt
cec2013lsgo/cdatafiles/F13-p.txt
cec2013lsgo/cdatafiles/F13-s.txt
cec2013lsgo/cdatafiles/F13-w.txt
cec2013lsgo/cdatafiles/F13-xopt.txt
cec2013lsgo/cdatafiles/F14-R100.txt
cec2013lsgo/cdatafiles/F14-R25.txt
cec2013lsgo/cdatafiles/F14-R50.txt
cec2013lsgo/cdatafiles/F14-p.txt
cec2013lsgo/cdatafiles/F14-s.txt
cec2013lsgo/cdatafiles/F14-w.txt
cec2013lsgo/cdatafiles/F14-xopt.txt
cec2013lsgo/cdatafiles/F15-xopt.txt
cec2013lsgo/cdatafiles/F2-xopt.txt
cec2013lsgo/cdatafiles/F3-xopt.txt
