Metadata-Version: 1.1
Name: cec2013lsgo
Version: 2.1
Summary: Package for benchmark for the Real     Large Scale Global Optimization session on IEEE     Congress on Evolutionary Computation CEC'2013
Home-page: https://github.com/dmolina/cec2013lsgo
Author: Daniel Molina
Author-email: dmolina@decsai.ugr.es
License: GPL V3
Platform: UNKNOWN
Classifier: Development Status :: 5 - Production/Stable
Classifier: License :: OSI Approved :: GNU General Public License v3 or later (GPLv3+)
